{
  "annotations": {
    "list": [
      {
        "builtIn": 1,
        "datasource": {
          "type": "grafana",
          "uid": "-- Grafana --"
        },
        "enable": true,
        "hide": true,
        "iconColor": "rgba(0, 211, 255, 1)",
        "name": "Annotations & Alerts",
        "type": "dashboard"
      }
    ]
  },
  "editable": true,
  "fiscalYearStartMonth": 0,
  "graphTooltip": 1,
  "id": null,
  "links": [],
  "liveNow": false,
  "panels": [
    {
      "datasource": {
        "type": "prometheus",
        "uid": "prometheus"
      },
      "fieldConfig": {
        "defaults": {
          "color": {
            "mode": "palette-classic"
          },
          "custom": {
            "axisCenteredZero": false,
            "axisColorMode": "text",
            "axisLabel": "",
            "axisPlacement": "auto",
            "barAlignment": 0,
            "drawStyle": "line",
            "fillOpacity": 20,
            "gradientMode": "none",
            "hideFrom": {
              "tooltip": false,
              "viz": false,
              "legend": false
            },
            "lineInterpolation": "smooth",
            "lineWidth": 2,
            "pointSize": 5,
            "scaleDistribution": {
              "type": "linear"
            },
            "showPoints": "auto",
            "spanNulls": false,
            "stacking": {
              "group": "A",
              "mode": "none"
            },
            "thresholdsStyle": {
              "mode": "off"
            }
          },
          "mappings": [],
          "thresholds": {
            "mode": "absolute",
            "steps": [
              {
                "color": "green",
                "value": null
              }
            ]
          },
          "unit": "short"
        },
        "overrides": []
      },
      "gridPos": {
        "h": 8,
        "w": 12,
        "x": 0,
        "y": 0
      },
      "id": 1,
      "options": {
        "legend": {
          "calcs": [
            "last",
            "sum"
          ],
          "displayMode": "table",
          "placement": "bottom",
          "showLegend": true
        },
        "tooltip": {
          "mode": "single",
          "sort": "none"
        }
      },
      "targets": [
        {
          "datasource": {
            "type": "prometheus",
            "uid": "prometheus"
          },
          "editorMode": "code",
          "expr": "rate(openfatture_payment_transactions_imported_total[5m])",
          "legendFormat": "{{bank_preset}} - {{status}}",
          "range": true,
          "refId": "A"
        }
      ],
      "title": "📥 Transactions Imported (rate/5m)",
      "type": "timeseries"
    },
    {
      "datasource": {
        "type": "prometheus",
        "uid": "prometheus"
      },
      "fieldConfig": {
        "defaults": {
          "color": {
            "mode": "thresholds"
          },
          "mappings": [],
          "max": 100,
          "min": 0,
          "thresholds": {
            "mode": "absolute",
            "steps": [
              {
                "color": "red",
                "value": null
              },
              {
                "color": "yellow",
                "value": 50
              },
              {
                "color": "green",
                "value": 80
              }
            ]
          },
          "unit": "percent"
        },
        "overrides": []
      },
      "gridPos": {
        "h": 8,
        "w": 6,
        "x": 12,
        "y": 0
      },
      "id": 2,
      "options": {
        "orientation": "auto",
        "reduceOptions": {
          "values": false,
          "calcs": [
            "lastNotNull"
          ],
          "fields": ""
        },
        "showThresholdLabels": false,
        "showThresholdMarkers": true
      },
      "pluginVersion": "10.0.0",
      "targets": [
        {
          "datasource": {
            "type": "prometheus",
            "uid": "prometheus"
          },
          "editorMode": "code",
          "expr": "(sum(increase(openfatture_payment_reconciliations_performed_total{status=\"success\"}[24h])) / sum(increase(openfatture_payment_transactions_imported_total{status=\"success\"}[24h]))) * 100",
          "legendFormat": "Reconciliation Rate",
          "range": true,
          "refId": "A"
        }
      ],
      "title": "✅ Reconciliation Rate (24h)",
      "type": "gauge"
    },
    {
      "datasource": {
        "type": "prometheus",
        "uid": "prometheus"
      },
      "fieldConfig": {
        "defaults": {
          "color": {
            "mode": "thresholds"
          },
          "mappings": [],
          "thresholds": {
            "mode": "absolute",
            "steps": [
              {
                "color": "green",
                "value": null
              },
              {
                "color": "yellow",
                "value": 50
              },
              {
                "color": "red",
                "value": 100
              }
            ]
          },
          "unit": "short"
        },
        "overrides": []
      },
      "gridPos": {
        "h": 8,
        "w": 6,
        "x": 18,
        "y": 0
      },
      "id": 3,
      "options": {
        "colorMode": "value",
        "graphMode": "area",
        "justifyMode": "auto",
        "orientation": "auto",
        "reduceOptions": {
          "values": false,
          "calcs": [
            "lastNotNull"
          ],
          "fields": ""
        },
        "textMode": "auto"
      },
      "pluginVersion": "10.0.0",
      "targets": [
        {
          "datasource": {
            "type": "prometheus",
            "uid": "prometheus"
          },
          "editorMode": "code",
          "expr": "sum(openfatture_payment_unmatched_transactions_count)",
          "legendFormat": "Unmatched",
          "range": true,
          "refId": "A"
        }
      ],
      "title": "🔍 Unmatched Queue Size",
      "type": "stat"
    },
    {
      "datasource": {
        "type": "prometheus",
        "uid": "prometheus"
      },
      "fieldConfig": {
        "defaults": {
          "color": {
            "mode": "palette-classic"
          },
          "custom": {
            "hideFrom": {
              "tooltip": false,
              "viz": false,
              "legend": false
            }
          },
          "mappings": []
        },
        "overrides": []
      },
      "gridPos": {
        "h": 8,
        "w": 12,
        "x": 0,
        "y": 8
      },
      "id": 4,
      "options": {
        "displayLabels": [
          "percent"
        ],
        "legend": {
          "displayMode": "table",
          "placement": "right",
          "showLegend": true,
          "values": [
            "value",
            "percent"
          ]
        },
        "pieType": "pie",
        "reduceOptions": {
          "values": false,
          "calcs": [
            "lastNotNull"
          ],
          "fields": ""
        },
        "tooltip": {
          "mode": "single",
          "sort": "none"
        }
      },
      "targets": [
        {
          "datasource": {
            "type": "prometheus",
            "uid": "prometheus"
          },
          "editorMode": "code",
          "expr": "histogram_quantile(0.95, sum(rate(openfatture_payment_matching_confidence_scores_bucket[5m])) by (le, matcher_strategy))",
          "legendFormat": "{{matcher_strategy}} (p95)",
          "range": true,
          "refId": "A"
        }
      ],
      "title": "📊 Matching Confidence Distribution (p95)",
      "type": "piechart"
    },
    {
      "datasource": {
        "type": "prometheus",
        "uid": "prometheus"
      },
      "fieldConfig": {
        "defaults": {
          "color": {
            "mode": "palette-classic"
          },
          "custom": {
            "axisCenteredZero": false,
            "axisColorMode": "text",
            "axisLabel": "",
            "axisPlacement": "auto",
            "barAlignment": 0,
            "drawStyle": "bars",
            "fillOpacity": 70,
            "gradientMode": "none",
            "hideFrom": {
              "tooltip": false,
              "viz": false,
              "legend": false
            },
            "lineInterpolation": "linear",
            "lineWidth": 1,
            "pointSize": 5,
            "scaleDistribution": {
              "type": "linear"
            },
            "showPoints": "auto",
            "spanNulls": false,
            "stacking": {
              "group": "A",
              "mode": "normal"
            },
            "thresholdsStyle": {
              "mode": "off"
            }
          },
          "mappings": [],
          "thresholds": {
            "mode": "absolute",
            "steps": [
              {
                "color": "green",
                "value": null
              }
            ]
          }
        },
        "overrides": []
      },
      "gridPos": {
        "h": 8,
        "w": 12,
        "x": 12,
        "y": 8
      },
      "id": 5,
      "options": {
        "legend": {
          "calcs": [
            "sum"
          ],
          "displayMode": "table",
          "placement": "right",
          "showLegend": true
        },
        "tooltip": {
          "mode": "multi",
          "sort": "desc"
        }
      },
      "targets": [
        {
          "datasource": {
            "type": "prometheus",
            "uid": "prometheus"
          },
          "editorMode": "code",
          "expr": "increase(openfatture_payment_reminders_sent_total[1h])",
          "legendFormat": "{{reminder_strategy}} - {{notifier_type}}",
          "range": true,
          "refId": "A"
        }
      ],
      "title": "📧 Reminders Sent (hourly)",
      "type": "timeseries"
    },
    {
      "datasource": {
        "type": "prometheus",
        "uid": "prometheus"
      },
      "fieldConfig": {
        "defaults": {
          "color": {
            "mode": "thresholds"
          },
          "custom": {
            "align": "auto",
            "cellOptions": {
              "type": "auto"
            },
            "inspect": false
          },
          "mappings": [],
          "thresholds": {
            "mode": "absolute",
            "steps": [
              {
                "color": "green",
                "value": null
              }
            ]
          }
        },
        "overrides": [
          {
            "matcher": {
              "id": "byName",
              "options": "Volume"
            },
            "properties": [
              {
                "id": "custom.cellOptions",
                "value": {
                  "type": "color-background"
                }
              },
              {
                "id": "color",
                "value": {
                  "mode": "continuous-GrYlRd"
                }
              }
            ]
          }
        ]
      },
      "gridPos": {
        "h": 8,
        "w": 24,
        "x": 0,
        "y": 16
      },
      "id": 6,
      "options": {
        "cellHeight": "sm",
        "footer": {
          "countRows": false,
          "fields": "",
          "reducer": [
            "sum"
          ],
          "show": false
        },
        "showHeader": true,
        "sortBy": [
          {
            "desc": true,
            "displayName": "Volume"
          }
        ]
      },
      "pluginVersion": "10.0.0",
      "targets": [
        {
          "datasource": {
            "type": "prometheus",
            "uid": "prometheus"
          },
          "editorMode": "code",
          "expr": "topk(10, sum(increase(openfatture_payment_transactions_imported_total[24h])) by (bank_preset))",
          "format": "table",
          "legendFormat": "__auto",
          "range": true,
          "refId": "A"
        }
      ],
      "title": "🏦 Top Banks by Import Volume (24h)",
      "transformations": [
        {
          "id": "organize",
          "options": {
            "excludeByName": {
              "Time": true
            },
            "indexByName": {},
            "renameByName": {
              "Value": "Volume",
              "bank_preset": "Bank"
            }
          }
        }
      ],
      "type": "table"
    }
  ],
  "refresh": "30s",
  "schemaVersion": 38,
  "style": "dark",
  "tags": [
    "payment",
    "openfatture",
    "reconciliation"
  ],
  "templating": {
    "list": []
  },
  "time": {
    "from": "now-24h",
    "to": "now"
  },
  "timepicker": {},
  "timezone": "",
  "title": "💰 OpenFatture Payment Tracking",
  "uid": "openfatture-payment-tracking",
  "version": 1,
  "weekStart": ""
}
